[
  {
    "value": "Speed Leggings",
    "title": "Speed"
  },
  {
    "value": "Pulse Leggings",
    "title": "Pulse"
  },
  {
    "value": "Vital Seamless 2.0 Leggings",
    "title": "Vital"
  },
  {
    "value": "Training Leggings",
    "title": "Training"
  },
  {
    "value": "Training Cropped Leggings",
    "title": "Cropped"
  },
  {
    "value": "Energy Seamless Leggings",
    "title": "Seamless"
  },
  {
    "value": "Flex High Waisted Leggings",
    "title": "High Waisted"
  },
  {
    "value": "KK Fit 7/8  Leggings",
    "title": "KK Fit"
  },
  {
    "value": "Studio Leggings",
    "title": "Studio"
  },
  {
    "value": "Zone Graphic Leggings",
    "title": "Graphic"
  },
  {
    "value": "Vision Leggings",
    "title": "Vision"
  },
  {
    "value": "GS Power Support Leggings",
    "title": "Power Support"
  }
]
